oheye/__init__.py
oheye/analogIn.py
oheye/analog_in.py
oheye/osc_out.py
oheye-1.0.4.dist-info/METADATA
oheye-1.0.4.dist-info/RECORD
oheye-1.0.4.dist-info/WHEEL
oheye-1.0.4.dist-info/top_level.txt
