Metadata-Version: 2.1
Name: oheye
Version: 1.0.4
Summary: A library for the Modern Device Oh Eye analog input board for Raspberry Pi.
Home-page: https://github.com/fluxly/oheye
Author: Modern Device
Author-email: shawn@as220.org
License: MIT
Platform: UNKNOWN
Classifier: Programming Language :: Python :: 3
Classifier: License :: OSI Approved :: MIT License
Classifier: Operating System :: OS Independent
Requires-Dist: spidev
Requires-Dist: python-osc
